deposit_amount.py
home_loan.py
personal_loan.py
vehicle_loan.py
withdraw_amount.py
nubank-0.0.1.dist-info/License.txt
nubank-0.0.1.dist-info/METADATA
nubank-0.0.1.dist-info/WHEEL
nubank-0.0.1.dist-info/top_level.txt
nubank-0.0.1.dist-info/RECORD
