Metadata-Version: 2.1
Name: nubank
Version: 0.0.1
Summary: This package provides some bank functions
Home-page: https://github.com/naga99552/publish/nubank
Author: Nagababu
Author-email: nagababuupputuri52@gmail.com
License: UNKNOWN
Platform: UNKNOWN
Requires-Dist: django (~=3.1.5)
